flux0_stream/__init__.py
flux0_stream/json.py
flux0_stream/patches.py
flux0_stream/py.typed
flux0_stream/types.py
flux0_stream/emitter/api.py
flux0_stream/emitter/memory.py
flux0_stream/frameworks/__init__.py
flux0_stream/frameworks/langchain.py
flux0_stream/store/api.py
flux0_stream/store/memory.py
flux0_stream-0.1.0b2.dist-info/METADATA
flux0_stream-0.1.0b2.dist-info/WHEEL
flux0_stream-0.1.0b2.dist-info/RECORD
