Metadata-Version: 2.4
Name: flux0-stream
Version: 0.1.0b2
Requires-Python: >=3.12
Requires-Dist: flux0-core==0.1.0-beta.2
Requires-Dist: jsonpatch>=1.33
Provides-Extra: langchain
Requires-Dist: langchain-core>=0.3.39; extra == 'langchain'
